aegis/__init__.py
aegis/__main__.py
aegis/cli.py
aegis/core/analyzer.py
aegis/core/connectors.py
aegis/core/library.py
aegis/core/models.py
aegis/core/plugins.py
aegis/core/reporting.py
aegis/core/database/__init__.py
aegis/core/database/manager.py
aegis/core/evaluators/__init__.py
aegis/core/evaluators/base.py
aegis/core/evaluators/code_security.py
aegis/core/evaluators/pii.py
aegis/core/evaluators/secrets.py
aegis/prompts/__init__.py
aegis/prompts/bias_harmful_content.json
aegis/prompts/code_generation_exploits.json
aegis/prompts/data_exfiltration.json
aegis/prompts/direct_prompt_injection.json
aegis/prompts/indirect_prompt_injection.json
aegis/prompts/jailbreaking_roleplaying.json
aegis/prompts/misinformation_deception.json
aegis/prompts/privacy_confidentiality.json
aegis/web_interface/Aegis.py
aegis/web_interface/pages/1_Security_Dashboard.py
aegis_redteam_framework-1.0.6.dist-info/licenses/LICENSE.txt
aegis_redteam_framework-1.0.6.dist-info/METADATA
aegis_redteam_framework-1.0.6.dist-info/WHEEL
aegis_redteam_framework-1.0.6.dist-info/entry_points.txt
aegis_redteam_framework-1.0.6.dist-info/top_level.txt
aegis_redteam_framework-1.0.6.dist-info/RECORD
