Metadata-Version: 2.4
Name: aegis-redteam-framework
Version: 1.0.6
Summary: An Open-Source LLM Red Teaming & Evaluation Framework
Author-email: Ruchir Kulkarni <ruchirkulkarni22@gmail.com>
Project-URL: Homepage, https://github.com/ruchirk22/aegis
Project-URL: Bug Tracker, https://github.com/ruchirk22/aegis/issues
Classifier: Programming Language :: Python :: 3
Classifier: License :: OSI Approved :: Apache Software License
Classifier: Operating System :: OS Independent
Classifier: Topic :: Scientific/Engineering :: Artificial Intelligence
Classifier: Topic :: Security
Requires-Python: >=3.9
License-File: LICENSE.txt
Requires-Dist: typer[all]
Requires-Dist: rich
Requires-Dist: plotly
Requires-Dist: pandas
Requires-Dist: google-generativeai
Requires-Dist: openai
Requires-Dist: anthropic
Requires-Dist: python-dotenv
Requires-Dist: requests
Requires-Dist: fpdf2
Requires-Dist: streamlit
Requires-Dist: kaleido
Requires-Dist: bandit
Dynamic: license-file
